CrafterColor/Color.py
CrafterColor/Errors.py
CrafterColor/Print.py
CrafterColor/__init__.py
CrafterColor/__test__.py
CrafterColor-0.2.2.dist-info/LICENCE.txt
CrafterColor-0.2.2.dist-info/METADATA
CrafterColor-0.2.2.dist-info/WHEEL
CrafterColor-0.2.2.dist-info/top_level.txt
CrafterColor-0.2.2.dist-info/RECORD
