Metadata-Version: 2.1
Name: CrafterColor
Version: 0.2.2
Summary: simplest and coolest color Library. print and menaged colors in Python!
Home-page: UNKNOWN
Author: Alawi Hussein Adnan Al Sayegh
Author-email: programming.laboratorys@gmail.com
License: MIT
Keywords: CrafterColor
Platform: UNKNOWN
Classifier: Development Status :: 5 - Production/Stable
Classifier: Intended Audience :: Developers
Classifier: Operating System :: Microsoft :: Windows :: Windows 10
Classifier: License :: OSI Approved :: MIT License
Classifier: Programming Language :: Python :: 3
